libcppjieba.cpython-35m-darwin.so
cppjieba/dict/hmm_model.utf8
cppjieba/dict/idf.utf8
cppjieba/dict/jieba.dict.utf8
cppjieba/dict/stop_words.utf8
cppjieba/dict/user.dict.utf8
cppjieba/dict/pos_dict/char_state_tab.utf8
cppjieba/dict/pos_dict/prob_emit.utf8
cppjieba/dict/pos_dict/prob_start.utf8
cppjieba/dict/pos_dict/prob_trans.utf8
cppjieba_py/__init__.py
cppjieba_py/analyse.py
cppjieba_py/posseg.py
cppjieba_py-0.0.12.dist-info/LICENSE
cppjieba_py-0.0.12.dist-info/METADATA
cppjieba_py-0.0.12.dist-info/WHEEL
cppjieba_py-0.0.12.dist-info/top_level.txt
cppjieba_py-0.0.12.dist-info/RECORD
