Metadata-Version: 2.1
Name: cppjieba-py
Version: 0.0.12
Summary: python bindings of cppjieba
Home-page: https://github.com/bung87/cppjieba-py/
Author: bung87,yeping zheng
License: UNKNOWN
Platform: UNKNOWN
Classifier: License :: OSI Approved :: MIT License
Classifier: Natural Language :: Chinese (Simplified)
Classifier: Natural Language :: Chinese (Traditional)
Classifier: Programming Language :: Python :: 2.7
Classifier: Programming Language :: Python :: 3.4
Classifier: Programming Language :: Python :: 3.5
Classifier: Programming Language :: Python :: 3.6
Classifier: Programming Language :: C++
Classifier: Operating System :: Unix
Classifier: Topic :: Text Processing :: Linguistic
Classifier: Topic :: Software Development :: Libraries :: Python Modules
Requires-Dist: pybind11 (>=2.2.0)
Requires-Dist: setuptools (>=0.7.0)
Provides-Extra: test
Requires-Dist: spec (==1.4.1) ; extra == 'test'
